dicioinformal/__init__.py
dicioinformal-0.5.1.dist-info/METADATA
dicioinformal-0.5.1.dist-info/WHEEL
dicioinformal-0.5.1.dist-info/top_level.txt
dicioinformal-0.5.1.dist-info/RECORD
