Metadata-Version: 2.1
Name: dicioinformal
Version: 0.5.1
Summary: search on dicionario informal
Home-page: https://github.com/olixao/dicioinformal
Author: OLixao
Author-email: contact@olixao.ml
License: UNKNOWN
Platform: UNKNOWN
